tree_sitter_rsm/__init__.py
tree_sitter_rsm/__init__.pyi
tree_sitter_rsm/_binding.abi3.so
tree_sitter_rsm/binding.c
tree_sitter_rsm/py.typed
tree_sitter_rsm/queries/highlights.scm
tree_sitter_rsm-0.7.0.dist-info/METADATA
tree_sitter_rsm-0.7.0.dist-info/WHEEL
tree_sitter_rsm-0.7.0.dist-info/top_level.txt
tree_sitter_rsm-0.7.0.dist-info/RECORD
